tests/__init__.py
tracor/__init__.py
tracor/core.py
tracor-0.1.3.dist-info/LICENSE
tracor-0.1.3.dist-info/METADATA
tracor-0.1.3.dist-info/WHEEL
tracor-0.1.3.dist-info/entry_points.txt
tracor-0.1.3.dist-info/top_level.txt
tracor-0.1.3.dist-info/RECORD
