Metadata-Version: 2.1
Name: tracor
Version: 0.1.3
Summary: A tool for running Python scripts line by line with error handling and reporting.
Home-page: https://github.com/ArlinJae/Tracor
Author: Jae Arlin
Author-email: arlin0jae@gmail.com
Classifier: Programming Language :: Python :: 3
Classifier: License :: OSI Approved :: MIT License
Classifier: Operating System :: OS Independent
Requires-Python: >=3.6
License-File: LICENSE
Requires-Dist: colorama
